{
  "location" : {
    "verticalAccuracy" : 3,
    "horizontalAccuracy" : 4.74865154026663,
    "timestamp" : 1751573598.999784,
    "latitude" : 45.181779075499286,
    "longitude" : -84.70028052494789,
    "altitude" : 310.059017887339
  },
  "placemark" : {
    "administrativeArea" : "MI",
    "name" : "1133 Thumb Lake Rd",
    "subThoroughfare" : "1133",
    "country" : "United States",
    "isoCountryCode" : "US",
    "postalCode" : "49795",
    "locality" : "Vanderbilt",
    "thoroughfare" : "Thumb Lake Rd",
    "subAdministrativeArea" : "Otsego County"
  },
  "heading" : {
    "trueHeading" : 321.3761291503906,
    "headingAccuracy" : 10.911735534667969
  }
}