{
  "heading" : {
    "trueHeading" : 177.4958953857422,
    "headingAccuracy" : 11.02677059173584
  },
  "placemark" : {
    "subThoroughfare" : "1133",
    "isoCountryCode" : "US",
    "postalCode" : "49795",
    "subAdministrativeArea" : "Otsego County",
    "thoroughfare" : "Thumb Lake Rd",
    "administrativeArea" : "MI",
    "country" : "United States",
    "locality" : "Vanderbilt",
    "name" : "1133 Thumb Lake Rd"
  },
  "location" : {
    "altitude" : 310.90255726873875,
    "timestamp" : 1751573755.999664,
    "latitude" : 45.18182062082038,
    "horizontalAccuracy" : 4.6898292367521215,
    "longitude" : -84.70031168188787,
    "verticalAccuracy" : 4.505109649951539
  }
}